pypi_miner/__init__.py
pypi_miner/cli.py
pypi_miner/miner.py
pypi_miner-1.0.4.dist-info/METADATA
pypi_miner-1.0.4.dist-info/WHEEL
pypi_miner-1.0.4.dist-info/entry_points.txt
pypi_miner-1.0.4.dist-info/top_level.txt
pypi_miner-1.0.4.dist-info/RECORD
