Metadata-Version: 2.4
Name: pypi-miner
Version: 1.0.4
Summary: Mine and extract complete package lists from PyPI registry
Author-email: Rinalic <rinalic39@gmail.com>
License: MIT
Project-URL: Homepage, https://github.com/oraoraoraaa/Package-List-Miner
Project-URL: Repository, https://github.com/oraoraoraaa/Package-List-Miner
Project-URL: Issues, https://github.com/oraoraoraaa/Package-List-Miner/issues
Keywords: pypi,python,package-mining,data-mining,registry
Classifier: Development Status :: 4 - Beta
Classifier: Intended Audience :: Developers
Classifier: License :: OSI Approved :: MIT License
Classifier: Programming Language :: Python :: 3
Classifier: Programming Language :: Python :: 3.8
Classifier: Programming Language :: Python :: 3.9
Classifier: Programming Language :: Python :: 3.10
Classifier: Programming Language :: Python :: 3.11
Classifier: Programming Language :: Python :: 3.12
Classifier: Topic :: Software Development :: Libraries
Requires-Python: >=3.8
Requires-Dist: requests>=2.31.0
Requires-Dist: tqdm>=4.66.0
